heir/__init__.py
heir/abc
heir/heir-opt
heir/heir-translate
heir/interfaces.py
heir/libopenfhe.so
heir/mlir_emitter.py
heir/pipeline.py
heir/backends/__init__.py
heir/backends/cleartext.py
heir/backends/openfhe/__init__.py
heir/backends/openfhe/backend.py
heir/backends/openfhe/config.py
heir/backends/util/__init__.py
heir/backends/util/common.py
heir/backends/util/cpp_compiler.py
heir/backends/util/pybind_helpers.py
heir/cereal/include/cereal/access.hpp
heir/cereal/include/cereal/cereal.hpp
heir/cereal/include/cereal/macros.hpp
heir/cereal/include/cereal/specialize.hpp
heir/cereal/include/cereal/version.hpp
heir/cereal/include/cereal/archives/adapters.hpp
heir/cereal/include/cereal/archives/binary.hpp
heir/cereal/include/cereal/archives/json.hpp
heir/cereal/include/cereal/archives/portable_binary.hpp
heir/cereal/include/cereal/archives/xml.hpp
heir/cereal/include/cereal/details/helpers.hpp
heir/cereal/include/cereal/details/polymorphic_impl.hpp
heir/cereal/include/cereal/details/polymorphic_impl_fwd.hpp
heir/cereal/include/cereal/details/static_object.hpp
heir/cereal/include/cereal/details/traits.hpp
heir/cereal/include/cereal/details/util.hpp
heir/cereal/include/cereal/external/LICENSE
heir/cereal/include/cereal/external/base64.hpp
heir/cereal/include/cereal/external/rapidjson/LICENSE
heir/cereal/include/cereal/external/rapidjson/allocators.h
heir/cereal/include/cereal/external/rapidjson/cursorstreamwrapper.h
heir/cereal/include/cereal/external/rapidjson/document.h
heir/cereal/include/cereal/external/rapidjson/encodedstream.h
heir/cereal/include/cereal/external/rapidjson/encodings.h
heir/cereal/include/cereal/external/rapidjson/filereadstream.h
heir/cereal/include/cereal/external/rapidjson/filewritestream.h
heir/cereal/include/cereal/external/rapidjson/fwd.h
heir/cereal/include/cereal/external/rapidjson/istreamwrapper.h
heir/cereal/include/cereal/external/rapidjson/memorybuffer.h
heir_py-0.0.2.dist-info/METADATA
heir_py-0.0.2.dist-info/WHEEL
heir_py-0.0.2.dist-info/top_level.txt
heir_py-0.0.2.dist-info/RECORD
heir_py-0.0.2.dist-info/licenses/LICENSE
