Metadata-Version: 2.4
Name: heir_py
Version: 0.0.2
Summary: The HEIR compiler
Author-email: Jeremy Kun <jkun@google.com>, Asra Ali <asraa@google.com>, Alexander Viand <alexander.viand@intel.com>
License-Expression: MIT AND Apache-2.0
Project-URL: Homepage, https://heir.dev
Project-URL: Issues, https://github.com/google/heir/issues
Classifier: Topic :: Security :: Cryptography
Classifier: Intended Audience :: Developers
Classifier: Topic :: Software Development :: Compilers
Requires-Python: >=3.11
License-File: LICENSE
Requires-Dist: numba>=0.61.0
Requires-Dist: numpy>=2.0.2
Requires-Dist: llvmlite>=0.44.0
Requires-Dist: pybind11>=2.13.6
Requires-Dist: pybind11_global>=2.13.6
Requires-Dist: colorama>=0.4.6
Requires-Dist: absl-py>=2.1.0
Dynamic: license-file
